LICENSE
MANIFEST.in
README.md
setup.py
drf_pdf_renderer/__init__.py
drf_pdf_renderer/apps.py
drf_pdf_renderer/mixins.py
drf_pdf_renderer/renderer.py
drf_pdf_renderer/utils.py
drf_pdf_renderer.egg-info/PKG-INFO
drf_pdf_renderer.egg-info/SOURCES.txt
drf_pdf_renderer.egg-info/dependency_links.txt
drf_pdf_renderer.egg-info/requires.txt
drf_pdf_renderer.egg-info/top_level.txt
drf_pdf_renderer/templates/pdf/base_landscape.html
drf_pdf_renderer/templates/pdf/base_portrait.html
drf_pdf_renderer/templates/pdf/list_landscape.html
drf_pdf_renderer/templates/pdf/list_portrait.html
drf_pdf_renderer/templatetags/__init__.py
drf_pdf_renderer/templatetags/pdf_tags.py